korouge_score/__init__.py
korouge_score/create_pyrouge_files.py
korouge_score/io.py
korouge_score/io_test.py
korouge_score/rouge.py
korouge_score/rouge_scorer.py
korouge_score/rouge_scorer_test.py
korouge_score/scoring.py
korouge_score/scoring_test.py
korouge_score/test_util.py
korouge_score/tokenize2.py
korouge_score/tokenize_test.py
korouge_score/tokenizers.py
korouge_score/tokenizers_test.py
korouge_score-0.1.4.dist-info/LICENSE
korouge_score-0.1.4.dist-info/METADATA
korouge_score-0.1.4.dist-info/WHEEL
korouge_score-0.1.4.dist-info/top_level.txt
korouge_score-0.1.4.dist-info/RECORD
