Metadata-Version: 2.1
Name: korouge-score
Version: 0.1.4
Summary: Pure python implementation of ROUGE-1.5.5. for korean
Home-page: https://github.com/HeegyuKim/korouge/
Author: Heegyu Kim
Author-email: heekue83@gmail.com
Classifier: Programming Language :: Python :: 3
Classifier: License :: OSI Approved :: Apache Software License
Classifier: Operating System :: OS Independent
Requires-Python: >=3.7
License-File: LICENSE
Requires-Dist: absl-py
Requires-Dist: nltk
Requires-Dist: numpy
Requires-Dist: six (>=1.14.0)
